django_silly_search-0.1.2.dist-info/DESCRIPTION.rst
django_silly_search-0.1.2.dist-info/METADATA
django_silly_search-0.1.2.dist-info/RECORD
django_silly_search-0.1.2.dist-info/WHEEL
django_silly_search-0.1.2.dist-info/metadata.json
django_silly_search-0.1.2.dist-info/top_level.txt
silly_search/__init__.py
silly_search/utils.py
