Metadata-Version: 1.1
Name: django-silly-search
Version: 0.1.2
Summary: Really simple django-app for search by Q-expressions
Home-page: https://github.com/Egregors/django-silly-search
Author: Vadim Iskuchekov
Author-email: egregors@yandex.ru
License: BSD
Download-URL: https://github.com/Egregors/django-silly-search/tarball/master
Keywords: django
Platform: UNKNOWN
Classifier: Development Status :: 4 - Beta
Classifier: Environment :: Web Environment
Classifier: Intended Audience :: Developers
Classifier: License :: OSI Approved :: BSD License
Classifier: Operating System :: OS Independent
Classifier: Programming Language :: Python
Classifier: Programming Language :: Python :: 3.4
Classifier: Programming Language :: Python :: 3.5
Classifier: Framework :: Django
